src/__init__.py
src/classifier.py
src/cost_estimator.py
src/eval_JSON_results.py
src/jobs.py
src/prompt_library.py
src/pubmed_fetcher.py
src/relevance.py
src/scoring_guidelines.py
src/skim_and_km_api.py
src/triton_client.py
src/utils.py
skimgpt-1.2.dist-info/METADATA
skimgpt-1.2.dist-info/WHEEL
skimgpt-1.2.dist-info/entry_points.txt
skimgpt-1.2.dist-info/top_level.txt
skimgpt-1.2.dist-info/RECORD
