Metadata-Version: 2.4
Name: skimgpt
Version: 1.2
Summary: Biomedical Knowledge Mining with co-occurrence modeling and LLMs
Author-email: Ron Stewart <rstewart@morgridge.org>, Rob Millikin <rmillikin@morgridge.org>, Kevin George <kshinegeorge@morgridge.org>, Jack Freeman <jfreeman@morgridge.org>
Maintainer-email: Ron Stewart <rstewart@morgridge.org>, Rob Millikin <rmillikin@morgridge.org>, Kevin George <kshinegeorge@morgridge.org>, Jack Freeman <jfreeman@morgridge.org>
License: MIT
Project-URL: Homepage, https://github.com/stewart-lab/skimgpt
Project-URL: Repository, https://github.com/stewart-lab/skimgpt.git
Project-URL: Documentation, https://github.com/stewart-lab/skimgpt#readme
Project-URL: Bug Tracker, https://github.com/stewart-lab/skimgpt/issues
Keywords: biomedical,nlp,co-occurrence,knowledge-mining,LLMs,literature-analysis,skim
Classifier: Development Status :: 3 - Alpha
Classifier: Intended Audience :: Science/Research
Classifier: Topic :: Scientific/Engineering :: Bio-Informatics
Classifier: Topic :: Scientific/Engineering :: Artificial Intelligence
Classifier: License :: OSI Approved :: MIT License
Classifier: Programming Language :: Python :: 3
Classifier: Programming Language :: Python :: 3.9
Classifier: Programming Language :: Python :: 3.10
Classifier: Programming Language :: Python :: 3.11
Classifier: Programming Language :: Python :: 3.12
Requires-Python: >=3.10
Requires-Dist: pandas>=1.3.0
Requires-Dist: numpy>=1.21.0
Requires-Dist: openai>=1.0.0
Requires-Dist: biopython>=1.79
Requires-Dist: requests>=2.25.0
Requires-Dist: vllm>=0.6.0
Requires-Dist: tiktoken>=0.7.0
Requires-Dist: htcondor>=24.6.1
Provides-Extra: dev
Requires-Dist: pytest>=6.0; extra == "dev"
Requires-Dist: black>=21.0; extra == "dev"
Requires-Dist: flake8>=3.8; extra == "dev"
Requires-Dist: mypy>=0.910; extra == "dev"
Requires-Dist: build>=0.7.0; extra == "dev"
Requires-Dist: twine>=3.4.0; extra == "dev"
